additional_functions/__init__.py
additional_functions/arithmetic.py
additional_functions/binary_search_tree.py
additional_functions/combinatorics.py
additional_functions/factorials.py
additional_functions/hash_table.py
additional_functions/linked_list.py
additional_functions/progressions.py
additional_functions/roman_arabic_numerals.py
additional_functions/sortings.py
additional_functions/subarrays.py
additional_functions-0.16.1.dist-info/METADATA
additional_functions-0.16.1.dist-info/WHEEL
additional_functions-0.16.1.dist-info/top_level.txt
additional_functions-0.16.1.dist-info/RECORD
