Metadata-Version: 2.1
Name: additional-functions
Version: 0.16.1
Summary: AdditionalFunctions
Author: s0urce
Author-email: boyarkin.gleb@gmail.com
Classifier: Programming Language :: Python :: 3
Classifier: License :: OSI Approved :: MIT License
Classifier: Operating System :: OS Independent
